[{"name":"Jacky-winter","scientific":"Microeca fascinans","overallProb":0.3103448275862069,"contribution":0.23060172633554227,"rarity":0.7430500070811917,"seasonal":"","monthly":null,"flags":[]},{"name":"Australian Pipit","scientific":"Anthus australis","overallProb":0.3620689655172414,"contribution":0.20631602586944467,"rarity":0.5698252143060852,"seasonal":"","monthly":null,"flags":[]},{"name":"Brown Falcon","scientific":"Falco berigora","overallProb":0.20689655172413793,"contribution":0.16486804082313083,"rarity":0.7968621973117991,"seasonal":"","monthly":null,"flags":[]},{"name":"Nankeen Kestrel","scientific":"Falco cenchroides","overallProb":0.39655172413793105,"contribution":0.13138102264039125,"rarity":0.3313086657888127,"seasonal":"","monthly":null,"flags":[]},{"name":"White-winged Chough","scientific":"Corcorax melanorhamphos","overallProb":0.3448275862068966,"contribution":0.10798498085365245,"rarity":0.3131564444755921,"seasonal":"","monthly":null,"flags":[]},{"name":"Zebra Finch","scientific":"Taeniopygia guttata","overallProb":0.10344827586206896,"contribution":0.09190062654453926,"rarity":0.8883727232638795,"seasonal":"","monthly":null,"flags":["not seen in last 3y"]},{"name":"Diamond Firetail","scientific":"Stagonopleura guttata","overallProb":0.10344827586206896,"contribution":0.08871817626103391,"rarity":0.8576090371899945,"seasonal":"","monthly":null,"flags":[]},{"name":"Singing Bushlark","scientific":"Mirafra javanica","overallProb":0.07530455162097908,"contribution":0.07329695413738979,"rarity":0.9733402903227698,"seasonal":"Oct-Jan","monthly":[0.11153815756225549,0.09778251897166368,0.04419073449933009,0.008278727316624934,0.013266310357941902,0.015305398580570562,0.013515453201103811,0.05223740033898616,0.049936018224043144,0.1745130647242613,0.14372019869953556,0.17937063697543243],"flags":[]},{"name":"Golden-headed Cisticola","scientific":"Cisticola exilis","overallProb":0.20689655172413793,"contribution":0.07129190561161147,"rarity":0.34457754378945543,"seasonal":"","monthly":null,"flags":[]},{"name":"Pacific Heron","scientific":"Ardea pacifica","overallProb":0.10344827586206896,"contribution":0.06881154455365274,"rarity":0.6651782640186431,"seasonal":"","monthly":null,"flags":[]},{"name":"Peaceful Dove","scientific":"Geopelia placida","overallProb":0.08620689655172414,"contribution":0.06591417311575087,"rarity":0.7646044081427101,"seasonal":"","monthly":null,"flags":["only 1 observer in last 3y"]},{"name":"Pallid Cuckoo","scientific":"Heteroscenes pallidus","overallProb":0.06896551724137931,"contribution":0.062326474115258115,"rarity":0.9037338746712427,"seasonal":"","monthly":null,"flags":["not seen in last 3y","unclear seasonal patterns"]},{"name":"Little Raven","scientific":"Corvus mellori","overallProb":0.1206896551724138,"contribution":0.06038948588358165,"rarity":0.5003700258925337,"seasonal":"","monthly":null,"flags":[]},{"name":"Brown Treecreeper","scientific":"Climacteris picumnus","overallProb":0.06896551724137931,"contribution":0.05730270948967202,"rarity":0.8308892876002443,"seasonal":"","monthly":null,"flags":[]},{"name":"Fairy Martin","scientific":"Petrochelidon ariel","overallProb":0.0979068014476987,"contribution":0.04583228350665494,"rarity":0.4681215485436761,"seasonal":"Aug-Jan","monthly":[0.13646255840229948,0.08865198906293348,0.053302203875639664,0.020619145663658744,0.016576401601302804,0.013410520014460747,0.020249028482613896,0.11664024915201032,0.18391544440548147,0.18539888517404335,0.16731660210771893,0.1723385894302215],"flags":[]},{"name":"Stubble Quail","scientific":"Coturnix pectoralis","overallProb":0.05172413793103448,"contribution":0.04575478803179032,"rarity":0.8845925686146128,"seasonal":"","monthly":null,"flags":["only 1 observer in last 3y","unclear seasonal patterns"]},{"name":"Rufous Songlark","scientific":"Cincloramphus mathewsi","overallProb":0.05593019899143569,"contribution":0.04482267010166206,"rarity":0.8014037301838589,"seasonal":"Oct-Dec","monthly":[0.07284374429444807,0.033065679044856244,0.009486779522077882,0.005974944397998394,0.008121949488608005,0.0,0.004512719398391707,0.005331305455514523,0.07676108313796548,0.17108863163897714,0.1714848193657934,0.11249073215259742],"flags":["only 1 observer in last 3y"]},{"name":"Pied Butcherbird","scientific":"Cracticus nigrogularis","overallProb":0.06896551724137931,"contribution":0.04447037712373428,"rarity":0.6448204682941471,"seasonal":"","monthly":null,"flags":["only 1 observer in last 3y"]},{"name":"Restless Flycatcher","scientific":"Myiagra inquieta","overallProb":0.05172413793103448,"contribution":0.040214262130250096,"rarity":0.7774757345181685,"seasonal":"","monthly":null,"flags":["not seen in last 3y"]},{"name":"Double-barred Finch","scientific":"Stizoptera bichenovii","overallProb":0.05172413793103448,"contribution":0.033497585858094696,"rarity":0.6476199932564974,"seasonal":"","monthly":null,"flags":["only 1 observer in last 3y"]},{"name":"Straw-necked Ibis","scientific":"Threskiornis spinicollis","overallProb":0.08620689655172414,"contribution":0.032926330182713855,"rarity":0.3819454301194807,"seasonal":"","monthly":null,"flags":["only 1 observer in last 3y"]},{"name":"White-browed Babbler","scientific":"Pomatostomus superciliosus","overallProb":0.034482758620689655,"contribution":0.03279719564101629,"rarity":0.9511186735894724,"seasonal":"","monthly":null,"flags":["not seen in last 3y"]},{"name":"Brown Songlark","scientific":"Cincloramphus cruralis","overallProb":0.034482758620689655,"contribution":0.03232598026877364,"rarity":0.9374534277944355,"seasonal":"","monthly":null,"flags":["one off","unclear seasonal patterns"]},{"name":"Black-shouldered Kite","scientific":"Elanus axillaris","overallProb":0.06896551724137931,"contribution":0.032089967681815046,"rarity":0.4653045313863182,"seasonal":"","monthly":null,"flags":["not seen in last 3y","one off"]},{"name":"White-browed Woodswallow","scientific":"Artamus superciliosus","overallProb":0.034482758620689655,"contribution":0.032030725060350616,"rarity":0.9288910267501679,"seasonal":"","monthly":null,"flags":["not seen in last 3y","unclear seasonal patterns"]},{"name":"Black-fronted Dotterel","scientific":"Thinornis melanops","overallProb":0.06896551724137931,"contribution":0.03082645634157268,"rarity":0.44698361695280386,"seasonal":"","monthly":null,"flags":["not seen in last 3y"]},{"name":"Dusky Woodswallow","scientific":"Artamus cyanopterus","overallProb":0.06896551724137931,"contribution":0.029709018832038688,"rarity":0.430780773064561,"seasonal":"","monthly":null,"flags":[]},{"name":"Tree Martin","scientific":"Petrochelidon nigricans","overallProb":0.05172413793103448,"contribution":0.028653189369835304,"rarity":0.5539616611501492,"seasonal":"","monthly":null,"flags":[]},{"name":"Horsfield's Bronze-Cuckoo","scientific":"Chalcites basalis","overallProb":0.034482758620689655,"contribution":0.028063580590499754,"rarity":0.8138438371244929,"seasonal":"","monthly":null,"flags":["not seen in last 3y","one off","unclear seasonal patterns"]},{"name":"White-winged Triller","scientific":"Lalage tricolor","overallProb":0.034482758620689655,"contribution":0.025264402994517023,"rarity":0.7326676868409937,"seasonal":"","monthly":null,"flags":["not seen in last 3y","unclear seasonal patterns"]},{"name":"Brown Quail","scientific":"Synoicus ypsilophorus","overallProb":0.034482758620689655,"contribution":0.0243351524348219,"rarity":0.7057194206098351,"seasonal":"","monthly":null,"flags":["not seen in last 3y","one off"]},{"name":"Red-rumped Parrot","scientific":"Psephotus haematonotus","overallProb":0.2413793103448276,"contribution":0.021072616444158743,"rarity":0.08730083955437193,"seasonal":"","monthly":null,"flags":[]},{"name":"Yellow-rumped Thornbill","scientific":"Acanthiza chrysorrhoa","overallProb":0.1724137931034483,"contribution":0.02048520264138325,"rarity":0.11881417532002285,"seasonal":"","monthly":null,"flags":[]},{"name":"Leaden Flycatcher","scientific":"Myiagra rubecula","overallProb":0.034482758620689655,"contribution":0.020441621380115856,"rarity":0.5928070200233598,"seasonal":"","monthly":null,"flags":["not seen in last 3y","one off","unclear seasonal patterns"]},{"name":"White-plumed Honeyeater","scientific":"Ptilotula penicillata","overallProb":0.10344827586206896,"contribution":0.020304496443574127,"rarity":0.1962767989545499,"seasonal":"","monthly":null,"flags":["only 1 observer in last 3y"]},{"name":"Australasian/Hoary-headed Grebe","scientific":"Tachybaptus novaehollandiae/Poliocephalus poliocephalus","overallProb":0.017241379310344827,"contribution":0.01703076281675326,"rarity":0.987784243371689,"seasonal":"","monthly":null,"flags":["not seen in last 3y","one off"]},{"name":"Black-chinned Honeyeater","scientific":"Melithreptus gularis","overallProb":0.017241379310344827,"contribution":0.016710645187234852,"rarity":0.9692174208596214,"seasonal":"","monthly":null,"flags":["not seen in last 3y","one off"]},{"name":"Eastern Barn Owl","scientific":"Tyto javanica","overallProb":0.017241379310344827,"contribution":0.01656617205066123,"rarity":0.9608379789383513,"seasonal":"","monthly":null,"flags":["only 1 observer in last 3y","one off"]},{"name":"Satin Flycatcher","scientific":"Myiagra cyanoleuca","overallProb":0.017241379310344827,"contribution":0.01639311811119252,"rarity":0.9508008504491661,"seasonal":"","monthly":null,"flags":["not seen in last 3y","one off","unclear seasonal patterns"]},{"name":"Southern Whiteface","scientific":"Aphelocephala leucopsis","overallProb":0.017241379310344827,"contribution":0.01628933355472526,"rarity":0.9447813461740651,"seasonal":"","monthly":null,"flags":["not seen in last 3y","one off"]},{"name":"Hooded Robin","scientific":"Melanodryas cucullata","overallProb":0.017241379310344827,"contribution":0.01601459700034399,"rarity":0.9288466260199515,"seasonal":"","monthly":null,"flags":["not seen in last 3y","one off"]},{"name":"Musk Lorikeet","scientific":"Trichoglossus concinnus","overallProb":0.034482758620689655,"contribution":0.01559999771292737,"rarity":0.4523999336748938,"seasonal":"","monthly":null,"flags":["only 1 observer in last 3y","unclear seasonal patterns"]},{"name":"Striped Honeyeater","scientific":"Plectorhyncha lanceolata","overallProb":0.017241379310344827,"contribution":0.015399902757328617,"rarity":0.8931943599250598,"seasonal":"","monthly":null,"flags":["not seen in last 3y","one off","unclear seasonal patterns"]},{"name":"Sahul Brush Cuckoo","scientific":"Cacomantis variolosus","overallProb":0.017241379310344827,"contribution":0.014853210810952774,"rarity":0.8614862270352609,"seasonal":"","monthly":null,"flags":["not seen in last 3y","one off","unclear seasonal patterns"]},{"name":"Blue-billed Duck","scientific":"Oxyura australis","overallProb":0.017241379310344827,"contribution":0.014716267927855756,"rarity":0.8535435398156338,"seasonal":"","monthly":null,"flags":["not seen in last 3y","one off"]},{"name":"Australian Boobook","scientific":"Ninox boobook","overallProb":0.017241379310344827,"contribution":0.014635943769195435,"rarity":0.8488847386133352,"seasonal":"","monthly":null,"flags":["only 1 observer in last 3y","one off"]},{"name":"Rainbow Bee-eater","scientific":"Merops ornatus","overallProb":0.017241379310344827,"contribution":0.01384461152635286,"rarity":0.8029874685284659,"seasonal":"","monthly":null,"flags":["only 1 observer in last 3y","one off","unclear seasonal patterns"]},{"name":"Eastern Shrike-tit","scientific":"Falcunculus frontatus","overallProb":0.017241379310344827,"contribution":0.013690113847205743,"rarity":0.7940266031379332,"seasonal":"","monthly":null,"flags":["not seen in last 3y","one off"]},{"name":"Little Lorikeet","scientific":"Psitteuteles pusillus","overallProb":0.017241379310344827,"contribution":0.013647964312409026,"rarity":0.7915819301197236,"seasonal":"","monthly":null,"flags":["not seen in last 3y","one off","unclear seasonal patterns"]},{"name":"Peregrine Falcon","scientific":"Falco peregrinus","overallProb":0.017241379310344827,"contribution":0.013647964312409026,"rarity":0.7915819301197236,"seasonal":"","monthly":null,"flags":["not seen in last 3y","one off"]},{"name":"Fuscous Honeyeater","scientific":"Ptilotula fusca","overallProb":0.017241379310344827,"contribution":0.013329317774910095,"rarity":0.7731004309447855,"seasonal":"","monthly":null,"flags":["not seen in last 3y","one off"]},{"name":"Azure Kingfisher","scientific":"Ceyx azureus","overallProb":0.017241379310344827,"contribution":0.013270924127710615,"rarity":0.7697135994072156,"seasonal":"","monthly":null,"flags":["only 1 observer in last 3y","one off"]},{"name":"Australian Hobby","scientific":"Falco longipennis","overallProb":0.017241379310344827,"contribution":0.013123783577511516,"rarity":0.7611794474956679,"seasonal":"","monthly":null,"flags":["not seen in last 3y","one off"]},{"name":"Sacred Kingfisher","scientific":"Todiramphus sanctus","overallProb":0.05172413793103448,"contribution":0.013001661886877916,"rarity":0.25136546314630637,"seasonal":"","monthly":null,"flags":["not seen in last 3y","unclear seasonal patterns"]},{"name":"Olive-backed Oriole","scientific":"Oriolus sagittatus","overallProb":0.06896551724137931,"contribution":0.012993084641324438,"rarity":0.18839972729920434,"seasonal":"","monthly":null,"flags":["only 1 observer in last 3y","unclear seasonal patterns"]},{"name":"Buff-banded Rail","scientific":"Gallirallus philippensis","overallProb":0.017241379310344827,"contribution":0.01291127719360786,"rarity":0.7488540772292559,"seasonal":"","monthly":null,"flags":["not seen in last 3y","one off"]},{"name":"Noisy Friarbird","scientific":"Philemon corniculatus","overallProb":0.07679816429974727,"contribution":0.012131049524927292,"rarity":0.1579601496408061,"seasonal":"Sep-Jan","monthly":[0.09893448564123264,0.08565449876304121,0.062123036879353166,0.039690380963609107,0.0109527616455658,0.013683698278548762,0.01623641181125579,0.05662351488316886,0.13714139670312442,0.15064371888218298,0.13186813297011235,0.11802593417577212],"flags":["not seen in last 3y"]},{"name":"Rufous Whistler","scientific":"Pachycephala rufiventris","overallProb":0.08620689655172414,"contribution":0.01194656683022667,"rarity":0.13858017523062935,"seasonal":"","monthly":null,"flags":["not seen in last 3y","unclear seasonal patterns"]},{"name":"Australian Rufous Fantail","scientific":"Rhipidura rufifrons","overallProb":0.017241379310344827,"contribution":0.010650370851858815,"rarity":0.6177215094078113,"seasonal":"","monthly":null,"flags":["not seen in last 3y","one off","unclear seasonal patterns"]},{"name":"Wedge-tailed Eagle","scientific":"Aquila audax","overallProb":0.017241379310344827,"contribution":0.00972734136202992,"rarity":0.5641857989977354,"seasonal":"","monthly":null,"flags":["not seen in last 3y","one off"]},{"name":"Common Bronzewing","scientific":"Phaps chalcoptera","overallProb":0.017241379310344827,"contribution":0.009498261585934491,"rarity":0.5508991719842005,"seasonal":"","monthly":null,"flags":["not seen in last 3y","one off"]},{"name":"Brown Goshawk","scientific":"Tachyspiza fasciata","overallProb":0.017241379310344827,"contribution":0.00947359190879902,"rarity":0.5494683307103432,"seasonal":"","monthly":null,"flags":["not seen in last 3y","one off"]},{"name":"Bar-shouldered Dove","scientific":"Geopelia humeralis","overallProb":0.017241379310344827,"contribution":0.00917730079387054,"rarity":0.5322834460444913,"seasonal":"","monthly":null,"flags":["not seen in last 3y","one off"]},{"name":"Scarlet Myzomela","scientific":"Myzomela sanguinolenta","overallProb":0.017241379310344827,"contribution":0.008822673386049418,"rarity":0.5117150563908662,"seasonal":"","monthly":null,"flags":["only 1 observer in last 3y","one off","unclear seasonal patterns"]},{"name":"White-naped Honeyeater","scientific":"Melithreptus lunatus","overallProb":0.017241379310344827,"contribution":0.007824384628901377,"rarity":0.4538143084762799,"seasonal":"","monthly":null,"flags":["not seen in last 3y","one off"]},{"name":"Weebill","scientific":"Smicrornis brevirostris","overallProb":0.034482758620689655,"contribution":0.006969212689162181,"rarity":0.20210716798570325,"seasonal":"","monthly":null,"flags":["not seen in last 3y"]},{"name":"Striated Pardalote","scientific":"Pardalotus striatus","overallProb":0.034482758620689655,"contribution":0.006369925319148624,"rarity":0.18472783425531009,"seasonal":"","monthly":null,"flags":["not seen in last 3y"]},{"name":"Little Corella","scientific":"Cacatua sanguinea","overallProb":0.1206896551724138,"contribution":0.005798750257003407,"rarity":0.048046787843742514,"seasonal":"","monthly":null,"flags":[]},{"name":"Variegated Fairywren","scientific":"Malurus lamberti","overallProb":0.017241379310344827,"contribution":0.005444391117008655,"rarity":0.315774684786502,"seasonal":"","monthly":null,"flags":["not seen in last 3y","one off"]},{"name":"Bell Miner","scientific":"Manorina melanophrys","overallProb":0.017241379310344827,"contribution":0.0051253901707924085,"rarity":0.2972726299059597,"seasonal":"","monthly":null,"flags":["not seen in last 3y","one off"]},{"name":"Pacific Koel","scientific":"Eudynamys orientalis","overallProb":0.017241379310344827,"contribution":0.003663941329579358,"rarity":0.21250859711560277,"seasonal":"","monthly":null,"flags":["only 1 observer in last 3y","one off","unclear seasonal patterns"]},{"name":"Gray Teal","scientific":"Anas gracilis","overallProb":0.06896551724137931,"contribution":0.003393639688800654,"rarity":0.04920777548760948,"seasonal":"","monthly":null,"flags":["not seen in last 3y"]},{"name":"Satin Bowerbird","scientific":"Ptilonorhynchus violaceus","overallProb":0.034482758620689655,"contribution":0.0033816505526074966,"rarity":0.0980678660256174,"seasonal":"","monthly":null,"flags":["not seen in last 3y","one off"]},{"name":"Yellow-tailed Black-Cockatoo","scientific":"Zanda funerea","overallProb":0.017241379310344827,"contribution":0.003165379331771412,"rarity":0.1835920012427419,"seasonal":"","monthly":null,"flags":["not seen in last 3y","one off","unclear seasonal patterns"]},{"name":"White-throated Treecreeper","scientific":"Cormobates leucophaea","overallProb":0.05172413793103448,"contribution":0.0026851648773888633,"rarity":0.05191318762951802,"seasonal":"","monthly":null,"flags":["only 1 observer in last 3y"]},{"name":"Hardhead","scientific":"Aythya australis","overallProb":0.017241379310344827,"contribution":0.002517449155483736,"rarity":0.14601205101805667,"seasonal":"","monthly":null,"flags":["not seen in last 3y","one off"]},{"name":"Yellow Thornbill","scientific":"Acanthiza nana","overallProb":0.017241379310344827,"contribution":0.0024889593874801073,"rarity":0.14435964447384622,"seasonal":"","monthly":null,"flags":["not seen in last 3y","one off"]},{"name":"Eastern Rosella","scientific":"Platycercus eximius","overallProb":0.1206896551724138,"contribution":0.0024512613723359686,"rarity":0.02031045137078374,"seasonal":"","monthly":null,"flags":["not seen in last 3y"]},{"name":"Australian King-Parrot","scientific":"Alisterus scapularis","overallProb":0.05172413793103448,"contribution":0.0024272832686768986,"rarity":0.04692747652775337,"seasonal":"","monthly":null,"flags":["only 1 observer in last 3y"]},{"name":"White-faced Heron","scientific":"Egretta novaehollandiae","overallProb":0.1896551724137931,"contribution":0.0022235506936614724,"rarity":0.011724176384760492,"seasonal":"","monthly":null,"flags":[]},{"name":"Black-faced Cuckooshrike","scientific":"Coracina novaehollandiae","overallProb":0.10838757718571079,"contribution":0.0019012203741623414,"rarity":0.017540943561316063,"seasonal":"Sep-Mar","monthly":[0.15941546010736218,0.12733600796482913,0.11778186924899103,0.10170157407870772,0.047309126324925566,0.03182878084083207,0.020947392848884805,0.04594113537279809,0.14657514877776423,0.15416945655688274,0.16774173886413035,0.17990323524242158],"flags":[]},{"name":"Red-browed Firetail","scientific":"Neochmia temporalis","overallProb":0.06896551724137931,"contribution":0.0016101261239531539,"rarity":0.02334682879732073,"seasonal":"","monthly":null,"flags":[]},{"name":"Chestnut Teal","scientific":"Anas castanea","overallProb":0.017241379310344827,"contribution":0.0014096409465678321,"rarity":0.08175917490093426,"seasonal":"","monthly":null,"flags":["not seen in last 3y","one off"]},{"name":"Gray Shrikethrush","scientific":"Colluricincla harmonica","overallProb":0.017241379310344827,"contribution":0.0013036030008948603,"rarity":0.0756089740519019,"seasonal":"","monthly":null,"flags":["only 1 observer in last 3y","one off"]},{"name":"New Holland Honeyeater","scientific":"Phylidonyris novaehollandiae","overallProb":0.017241379310344827,"contribution":0.0011956353956863888,"rarity":0.06934685294981055,"seasonal":"","monthly":null,"flags":["not seen in last 3y","one off"]},{"name":"Australasian Grebe","scientific":"Tachybaptus novaehollandiae","overallProb":0.017241379310344827,"contribution":0.0011232948482797795,"rarity":0.06515110120022721,"seasonal":"","monthly":null,"flags":["not seen in last 3y","one off"]},{"name":"Golden Whistler","scientific":"Pachycephala pectoralis","overallProb":0.017241379310344827,"contribution":0.0009190278213866977,"rarity":0.05330361364042847,"seasonal":"","monthly":null,"flags":["not seen in last 3y","one off"]},{"name":"Maned Duck","scientific":"Chenonetta jubata","overallProb":0.1724137931034483,"contribution":0.0006184115921894803,"rarity":0.0035867872346989856,"seasonal":"","monthly":null,"flags":[]},{"name":"Eastern Yellow Robin","scientific":"Eopsaltria australis","overallProb":0.017241379310344827,"contribution":0.0005993395051769428,"rarity":0.03476169130026268,"seasonal":"","monthly":null,"flags":["not seen in last 3y","one off"]},{"name":"Crested Pigeon","scientific":"Ocyphaps lophotes","overallProb":0.20689655172413793,"contribution":0.0004212115291137778,"rarity":0.002035855724049926,"seasonal":"","monthly":null,"flags":[]},{"name":"Masked Lapwing","scientific":"Vanellus miles","overallProb":0.10344827586206896,"contribution":0.0002421297209302545,"rarity":0.0023405873023257936,"seasonal":"","monthly":null,"flags":["not seen in last 3y"]},{"name":"Laughing Kookaburra","scientific":"Dacelo novaeguineae","overallProb":0.15517241379310345,"contribution":0.00023236158415354573,"rarity":0.001497441320100628,"seasonal":"","monthly":null,"flags":[]},{"name":"Yellow-faced Honeyeater","scientific":"Caligavis chrysops","overallProb":0.017241379310344827,"contribution":0.0001937848801521202,"rarity":0.011239523048822971,"seasonal":"","monthly":null,"flags":["not seen in last 3y","one off"]},{"name":"Brown Thornbill","scientific":"Acanthiza pusilla","overallProb":0.017241379310344827,"contribution":0.00019346171114046232,"rarity":0.011220779246146815,"seasonal":"","monthly":null,"flags":["not seen in last 3y","one off"]},{"name":"White-browed Scrubwren","scientific":"Sericornis frontalis","overallProb":0.017241379310344827,"contribution":0.00019215122970991965,"rarity":0.01114477132317534,"seasonal":"","monthly":null,"flags":["not seen in last 3y","one off"]},{"name":"Willie-wagtail","scientific":"Rhipidura leucophrys","overallProb":0.3793103448275862,"contribution":0.00018463475362483477,"rarity":0.0004867643504654735,"seasonal":"","monthly":null,"flags":[]},{"name":"Silvereye","scientific":"Zosterops lateralis","overallProb":0.017241379310344827,"contribution":0.00014943335253370547,"rarity":0.008667134446954917,"seasonal":"","monthly":null,"flags":["not seen in last 3y","one off"]},{"name":"Gray Butcherbird","scientific":"Cracticus torquatus","overallProb":0.034482758620689655,"contribution":0.00013346925398496047,"rarity":0.0038706083655638537,"seasonal":"","monthly":null,"flags":["not seen in last 3y"]},{"name":"Dusky Moorhen","scientific":"Gallinula tenebrosa","overallProb":0.017241379310344827,"contribution":0.00011964687304811136,"rarity":0.0069395186367904585,"seasonal":"","monthly":null,"flags":["only 1 observer in last 3y","one off"]},{"name":"Galah","scientific":"Eolophus roseicapilla","overallProb":0.08620689655172414,"contribution":0.00011203268305685363,"rarity":0.001299579123459502,"seasonal":"","monthly":null,"flags":["only 1 observer in last 3y"]},{"name":"Eurasian Coot","scientific":"Fulica atra","overallProb":0.017241379310344827,"contribution":8.883138901134271e-05,"rarity":0.005152220562657878,"seasonal":"","monthly":null,"flags":["not seen in last 3y","one off"]},{"name":"Pacific Black Duck","scientific":"Anas superciliosa","overallProb":0.13793103448275862,"contribution":8.711416348886389e-05,"rarity":0.0006315776852942632,"seasonal":"","monthly":null,"flags":["only 1 observer in last 3y"]},{"name":"Welcome Swallow","scientific":"Hirundo neoxena","overallProb":0.20689655172413793,"contribution":2.00330792551062e-05,"rarity":9.68265497330133e-05,"seasonal":"","monthly":null,"flags":[]},{"name":"Crimson Rosella","scientific":"Platycercus elegans","overallProb":0.017241379310344827,"contribution":1.5142719895050884e-05,"rarity":0.0008782777539129513,"seasonal":"","monthly":null,"flags":["not seen in last 3y","one off"]},{"name":"Gray Fantail","scientific":"Rhipidura albiscapa","overallProb":0.017241379310344827,"contribution":1.3655344844899908e-05,"rarity":0.0007920100010041947,"seasonal":"","monthly":null,"flags":["not seen in last 3y","one off"]},{"name":"Sulphur-crested Cockatoo","scientific":"Cacatua galerita","overallProb":0.41379310344827586,"contribution":7.978010133731144e-06,"rarity":1.928019115651693e-05,"seasonal":"","monthly":null,"flags":[]},{"name":"Pied Currawong","scientific":"Strepera graculina","overallProb":0.20689655172413793,"contribution":6.338722188872146e-06,"rarity":3.0637157246215376e-05,"seasonal":"","monthly":null,"flags":[]},{"name":"Superb Fairywren","scientific":"Malurus cyaneus","overallProb":0.3620689655172414,"contribution":3.640464542753573e-06,"rarity":1.0054616356176535e-05,"seasonal":"","monthly":null,"flags":[]},{"name":"Noisy Miner","scientific":"Manorina melanocephala","overallProb":0.08620689655172414,"contribution":3.3495580115381424e-06,"rarity":3.885487293384245e-05,"seasonal":"","monthly":null,"flags":[]},{"name":"Magpie-lark","scientific":"Grallina cyanoleuca","overallProb":0.5,"contribution":2.960536755481146e-06,"rarity":5.921073510962292e-06,"seasonal":"","monthly":null,"flags":[]},{"name":"Australian Raven","scientific":"Corvus coronoides","overallProb":0.3275862068965517,"contribution":8.256739667905814e-07,"rarity":2.5204784249396695e-06,"seasonal":"","monthly":null,"flags":[]},{"name":"Australian Magpie","scientific":"Gymnorhina tibicen","overallProb":0.5517241379310345,"contribution":3.403934168447892e-09,"rarity":6.169630680311804e-09,"seasonal":"","monthly":null,"flags":[]}]